pandora_storage_server_client/__init__.py
pandora_storage_server_client/pandora_client.py
pandora_storage_server_client-0.1.4.dist-info/LICENSE.txt
pandora_storage_server_client-0.1.4.dist-info/METADATA
pandora_storage_server_client-0.1.4.dist-info/WHEEL
pandora_storage_server_client-0.1.4.dist-info/top_level.txt
pandora_storage_server_client-0.1.4.dist-info/RECORD
