Metadata-Version: 2.1
Name: pandora-storage-server-client
Version: 0.1.4
Summary: Pandora Storage Server Client.
Author: Juan Carlos Juárez
Author-email: <jc.juarezgarcia@outlook.com>
Keywords: Storage,Key-Value,Server,NoSQL,Schemaless,GNU/Linux
License-File: LICENSE.txt
Requires-Dist: requests
